funman_demo/__init__.py
funman_demo/_version.py
funman_demo/box_plotter.py
funman_demo/handlers.py
funman_demo/plot.py
funman_demo/example/__init__.py
funman_demo/example/bilayer.py
funman_demo/example/chime.py
funman_demo/example/demo120822.py
funman_demo-1.5.0.dist-info/METADATA
funman_demo-1.5.0.dist-info/WHEEL
funman_demo-1.5.0.dist-info/top_level.txt
funman_demo-1.5.0.dist-info/RECORD
